{
  "category": [
    {
      "id": "512354626416234323frd490",
      "img": "../img/image 31.png",
      "type": "Автоматические анализаторые",
      "header": "Автоматический гематологический анализатор DF50 Vet",
      "price": 690000,
      "inbase": "В наличии",
      "cat": "Биохимические"
    },
    {
      "id": "512354626416234323frd491",
      "img": "../img/image 31 (1).png",
      "type": "Автоматические анализаторые",
      "header": "Автоматический гематологический анализатор DF50 Vet",
      "price": 690000,
      "inbase": "Нет в наличии",
      "cat": "Электрокардиографы"
    },
    {
      "id": "512354626416234323frd492",
      "img": "../img/image 31 (2).png",
      "type": "Автоматические анализаторые",
      "header": "Автоматический гематологический анализатор DF50 Vet",
      "price": 690000,
      "inbase": "В наличии",
      "cat": "Иммуно"
    },
    {
      "id": "512354626416234323frd493",
      "img": "../img/image 31 (3).png",
      "type": "Автоматические анализаторые",
      "header": "Автоматический гематологический анализатор DF50 Vet",
      "price": 690000,
      "inbase": "Нет в наличии",
      "cat": "Разное"
    },
    {
      "id": "512354626416234323frd494",
      "img": "../img/image 31.png",
      "type": "Автоматические анализаторые",
      "header": "Автоматический гематологический анализатор DF50 Vet",
      "price": 690000,
      "inbase": "В наличии",
      "cat": "Биологические"
    },
    {
      "id": "512354626416234323frd495",
      "img": "../img/image 31.png",
      "type": "Автоматические анализаторые",
      "header": "Автоматический гематологический анализатор DF50 Vet",
      "price": 690000,
      "inbase": "Нет в наличии",
      "cat": "Дозаторы"
    },
    {
      "id": "512354626416234323frd496",
      "img": "../img/image 31.png",
      "type": "Автоматические анализаторые",
      "header": "Автоматический гематологический анализатор DF50 Vet",
      "price": 690000,
      "inbase": "В наличии",
      "cat": "Центрифуги"
    },
    {
      "id": "512354626416234323frd497",
      "img": "../img/image 31.png",
      "type": "Автоматические анализаторые",
      "header": "Автоматический гематологический анализатор DF50 Vet",
      "price": 690000,
      "inbase": "Нет в наличии",
      "cat": "Рентген"
    },
    {
      "id": "512354626416234323frd498",
      "img": "../img/image 31 (3).png",
      "type": "Автоматические анализаторые",
      "header": "Автоматический гематологический анализатор DF50 Vet",
      "price": 690000,
      "inbase": "В наличии",
      "cat": "Функциональная"
    },
    {
      "id": "512354626416234323frd499",
      "img": "../img/image 31 (2).png",
      "type": "Автоматические анализаторые",
      "header": "Автоматический гематологический анализатор DF50 Vet",
      "price": 690000,
      "inbase": "Нет в наличии",
      "cat": "Терапия"
    },
    {
      "id": "512354626416234323frd410",
      "img": "../img/image 31 (3).png",
      "type": "Автоматические анализаторые",
      "header": "Автоматический гематологический анализатор DF50 Vet",
      "price": 690000,
      "inbase": "В наличии",
      "cat": "Экспресс"
    },
    {
      "id": "512354626416234323frd411",
      "img": "../img/image 31 (1).png",
      "type": "Автоматические анализаторые",
      "header": "Автоматический гематологический анализатор DF50 Vet",
      "price": 690000,
      "inbase": "Нет в наличии",
      "cat": "Коагулометры"
    },
    {
      "id": "512354626416234323frd412",
      "img": "../img/image 31 (2).png",
      "type": "Автоматические анализаторые",
      "header": "Автоматический гематологический анализатор DF50 Vet",
      "price": 690000,
      "inbase": "В наличии",
      "cat": "Гематологические"
    },
    {
      "id": "512354626416234323frd413",
      "img": "../img/image 31 (3).png",
      "type": "Автоматические анализаторые",
      "header": "Автоматический гематологический анализатор DF50 Vet",
      "price": 690000,
      "inbase": "Нет в наличии",
      "cat": "Биохимические"
    },
    {
      "id": "512354626416234323frd414",
      "img": "../img/image 31 (1).png",
      "type": "Автоматические анализаторые",
      "header": "Автоматический гематологический анализатор DF50 Vet",
      "price": 690000,
      "inbase": "В наличии",
      "cat": "Электрокардиографы"
    },
    {
      "id": "512354626416234323frd415",
      "img": "../img/image 31 (2).png",
      "type": "Автоматические анализаторые",
      "header": "Автоматический гематологический анализатор DF50 Vet",
      "price": 690000,
      "inbase": "Нет в наличии",
      "cat": "Иммуно"
    },
    {
      "id": "512354626416234323frd416",
      "img": "../img/image 31.png",
      "type": "Автоматические анализаторые",
      "header": "Автоматический гематологический анализатор DF50 Vet",
      "price": 690000,
      "inbase": "В наличии",
      "cat": "Разное"
    },
    {
      "id": "512354626416234323frd417",
      "img": "../img/image 31 (3).png",
      "type": "Автоматические анализаторые",
      "header": "Автоматический гематологический анализатор DF50 Vet",
      "price": 690000,
      "inbase": "Нет в наличии",
      "cat": "Биологические"
    },
    {
      "id": "512354626416234323frd418",
      "img": "../img/image 31 (1).png",
      "type": "Автоматические анализаторые",
      "header": "Автоматический гематологический анализатор DF50 Vet",
      "price": 690000,
      "inbase": "В наличии",
      "cat": "Дозаторы"
    },
    {
      "id": "512354626416234323frd419",
      "img": "../img/image 31 (3).png",
      "type": "Автоматические анализаторые",
      "header": "Автоматический гематологический анализатор DF50 Vet",
      "price": 690000,
      "inbase": "Нет в наличии",
      "cat": "Центрифуги"
    },
    {
      "id": "512354626416234323frd420",
      "img": "../img/image 31 (2).png",
      "type": "Автоматические анализаторые",
      "header": "Автоматический гематологический анализатор DF50 Vet",
      "price": 690000,
      "inbase": "В наличии",
      "cat": "Рентген"
    },
    {
      "id": "512354626416234323frd421",
      "img": "../img/image 31.png",
      "type": "Автоматические анализаторые",
      "header": "Автоматический гематологический анализатор DF50 Vet",
      "price": 690000,
      "inbase": "Нет в наличии",
      "cat": "Функциональная"
    },
    {
      "id": "512354626416234323frd422",
      "img": "../img/image 31 (1).png",
      "type": "Автоматические анализаторые",
      "header": "Автоматический гематологический анализатор DF50 Vet",
      "price": 690000,
      "inbase": "В наличии",
      "cat": "Терапия"
    },
    {
      "id": "512354626416234323frd423",
      "img": "../img/image 31 (3).png",
      "type": "Автоматические анализаторые",
      "header": "Автоматический гематологический анализатор DF50 Vet",
      "price": 690000,
      "inbase": "Нет в наличии",
      "cat": "Экспресс"
    },
    {
      "id": "512354626416234323frd424",
      "img": "../img/image 31 (2).png",
      "type": "Автоматические анализаторые",
      "header": "Автоматический гематологический анализатор DF50 Vet",
      "price": 690000,
      "inbase": "В наличии",
      "cat": "Коагулометры"
    },
    {
      "id": "512354626416234323frd425",
      "img": "../img/image 31 (3).png",
      "type": "Автоматические анализаторые",
      "header": "Автоматический гематологический анализатор DF50 Vet",
      "price": 690000,
      "inbase": "Нет в наличии",
      "cat": "Гематологические"
    },
    {
      "id": "512354626416234323frd426",
      "img": "../img/image 31 (1).png",
      "type": "Автоматические анализаторые",
      "header": "Автоматический гематологический анализатор DF50 Vet",
      "price": 690000,
      "inbase": "В наличии",
      "cat": "Гематологические"
    },
    {
      "id": "512354626416234323frd427",
      "img": "../img/image 31 (3).png",
      "type": "Автоматические анализаторые",
      "header": "Автоматический гематологический анализатор DF50 Vet",
      "price": 690000,
      "inbase": "Нет в наличии",
      "cat": "Биохимические"
    },
    {
      "id": "512354626416234323frd428",
      "img": "../img/image 31 (2).png",
      "type": "Автоматические анализаторые",
      "header": "Автоматический гематологический анализатор DF50 Vet",
      "price": 690000,
      "inbase": "В наличии",
      "cat": "Электрокардиографы"
    },
    {
      "id": "512354626416234323frd429",
      "img": "../img/image 31.png",
      "type": "Автоматические анализаторые",
      "header": "Автоматический гематологический анализатор DF50 Vet",
      "price": 690000,
      "inbase": "Нет в наличии",
      "cat": "Иммуно"
    }
  ],
  "zakazlar": [],
  "service": [
    {
      "id": "512354626416234323frd490",
      "img": "../img/image 31.png",
      "type": "Автоматические анализаторые",
      "header": "Автоматический гематологический анализатор DF50 Vet",
      "price": 690000,
      "inbase": "В наличии",
      "cat": "Биохимические"
    },
    {
      "id": "512354626416234323frd491",
      "img": "../img/image 31 (1).png",
      "type": "Автоматические анализаторые",
      "header": "Автоматический гематологический анализатор DF50 Vet",
      "price": 690000,
      "inbase": "Нет в наличии",
      "cat": "Электрокардиографы"
    },
    {
      "id": "512354626416234323frd492",
      "img": "../img/image 31 (2).png",
      "type": "Автоматические анализаторые",
      "header": "Автоматический гематологический анализатор DF50 Vet",
      "price": 690000,
      "inbase": "В наличии",
      "cat": "Иммуно"
    },
    {
      "id": "512354626416234323frd493",
      "img": "../img/image 31 (3).png",
      "type": "Автоматические анализаторые",
      "header": "Автоматический гематологический анализатор DF50 Vet",
      "price": 690000,
      "inbase": "Нет в наличии",
      "cat": "Разное"
    },
    {
      "id": "512354626416234323frd494",
      "img": "../img/image 31.png",
      "type": "Автоматические анализаторые",
      "header": "Автоматический гематологический анализатор DF50 Vet",
      "price": 690000,
      "inbase": "В наличии",
      "cat": "Биологические"
    },
    {
      "id": "512354626416234323frd495",
      "img": "../img/image 31.png",
      "type": "Автоматические анализаторые",
      "header": "Автоматический гематологический анализатор DF50 Vet",
      "price": 690000,
      "inbase": "Нет в наличии",
      "cat": "Дозаторы"
    },
    {
      "id": "512354626416234323frd496",
      "img": "../img/image 31.png",
      "type": "Автоматические анализаторые",
      "header": "Автоматический гематологический анализатор DF50 Vet",
      "price": 690000,
      "inbase": "В наличии",
      "cat": "Центрифуги"
    },
    {
      "id": "512354626416234323frd497",
      "img": "../img/image 31.png",
      "type": "Автоматические анализаторые",
      "header": "Автоматический гематологический анализатор DF50 Vet",
      "price": 690000,
      "inbase": "Нет в наличии",
      "cat": "Рентген"
    },
    {
      "id": "512354626416234323frd498",
      "img": "../img/image 31 (3).png",
      "type": "Автоматические анализаторые",
      "header": "Автоматический гематологический анализатор DF50 Vet",
      "price": 690000,
      "inbase": "В наличии",
      "cat": "Функциональная"
    },
    {
      "id": "512354626416234323frd499",
      "img": "../img/image 31 (2).png",
      "type": "Автоматические анализаторые",
      "header": "Автоматический гематологический анализатор DF50 Vet",
      "price": 690000,
      "inbase": "Нет в наличии",
      "cat": "Терапия"
    },
    {
      "id": "512354626416234323frd410",
      "img": "../img/image 31 (3).png",
      "type": "Автоматические анализаторые",
      "header": "Автоматический гематологический анализатор DF50 Vet",
      "price": 690000,
      "inbase": "В наличии",
      "cat": "Экспресс"
    },
    {
      "id": "512354626416234323frd411",
      "img": "../img/image 31 (1).png",
      "type": "Автоматические анализаторые",
      "header": "Автоматический гематологический анализатор DF50 Vet",
      "price": 690000,
      "inbase": "Нет в наличии",
      "cat": "Коагулометры"
    },
    {
      "id": "512354626416234323frd412",
      "img": "../img/image 31 (2).png",
      "type": "Автоматические анализаторые",
      "header": "Автоматический гематологический анализатор DF50 Vet",
      "price": 690000,
      "inbase": "В наличии",
      "cat": "Гематологические"
    },
    {
      "id": "512354626416234323frd413",
      "img": "../img/image 31 (3).png",
      "type": "Автоматические анализаторые",
      "header": "Автоматический гематологический анализатор DF50 Vet",
      "price": 690000,
      "inbase": "Нет в наличии",
      "cat": "Биохимические"
    },
    {
      "id": "512354626416234323frd414",
      "img": "../img/image 31 (1).png",
      "type": "Автоматические анализаторые",
      "header": "Автоматический гематологический анализатор DF50 Vet",
      "price": 690000,
      "inbase": "В наличии",
      "cat": "Электрокардиографы"
    },
    {
      "id": "512354626416234323frd415",
      "img": "../img/image 31 (2).png",
      "type": "Автоматические анализаторые",
      "header": "Автоматический гематологический анализатор DF50 Vet",
      "price": 690000,
      "inbase": "Нет в наличии",
      "cat": "Иммуно"
    },
    {
      "id": "512354626416234323frd416",
      "img": "../img/image 31.png",
      "type": "Автоматические анализаторые",
      "header": "Автоматический гематологический анализатор DF50 Vet",
      "price": 690000,
      "inbase": "В наличии",
      "cat": "Разное"
    },
    {
      "id": "512354626416234323frd417",
      "img": "../img/image 31 (3).png",
      "type": "Автоматические анализаторые",
      "header": "Автоматический гематологический анализатор DF50 Vet",
      "price": 690000,
      "inbase": "Нет в наличии",
      "cat": "Биологические"
    },
    {
      "id": "512354626416234323frd418",
      "img": "../img/image 31 (1).png",
      "type": "Автоматические анализаторые",
      "header": "Автоматический гематологический анализатор DF50 Vet",
      "price": 690000,
      "inbase": "В наличии",
      "cat": "Дозаторы"
    },
    {
      "id": "512354626416234323frd419",
      "img": "../img/image 31 (3).png",
      "type": "Автоматические анализаторые",
      "header": "Автоматический гематологический анализатор DF50 Vet",
      "price": 690000,
      "inbase": "Нет в наличии",
      "cat": "Центрифуги"
    },
    {
      "id": "512354626416234323frd420",
      "img": "../img/image 31 (2).png",
      "type": "Автоматические анализаторые",
      "header": "Автоматический гематологический анализатор DF50 Vet",
      "price": 690000,
      "inbase": "В наличии",
      "cat": "Рентген"
    },
    {
      "id": "512354626416234323frd421",
      "img": "../img/image 31.png",
      "type": "Автоматические анализаторые",
      "header": "Автоматический гематологический анализатор DF50 Vet",
      "price": 690000,
      "inbase": "Нет в наличии",
      "cat": "Функциональная"
    },
    {
      "id": "512354626416234323frd422",
      "img": "../img/image 31 (1).png",
      "type": "Автоматические анализаторые",
      "header": "Автоматический гематологический анализатор DF50 Vet",
      "price": 690000,
      "inbase": "В наличии",
      "cat": "Терапия"
    },
    {
      "id": "512354626416234323frd423",
      "img": "../img/image 31 (3).png",
      "type": "Автоматические анализаторые",
      "header": "Автоматический гематологический анализатор DF50 Vet",
      "price": 690000,
      "inbase": "Нет в наличии",
      "cat": "Экспресс"
    },
    {
      "id": "512354626416234323frd424",
      "img": "../img/image 31 (2).png",
      "type": "Автоматические анализаторые",
      "header": "Автоматический гематологический анализатор DF50 Vet",
      "price": 690000,
      "inbase": "В наличии",
      "cat": "Коагулометры"
    },
    {
      "id": "512354626416234323frd425",
      "img": "../img/image 31 (3).png",
      "type": "Автоматические анализаторые",
      "header": "Автоматический гематологический анализатор DF50 Vet",
      "price": 690000,
      "inbase": "Нет в наличии",
      "cat": "Гематологические"
    },
    {
      "id": "512354626416234323frd426",
      "img": "../img/image 31 (1).png",
      "type": "Автоматические анализаторые",
      "header": "Автоматический гематологический анализатор DF50 Vet",
      "price": 690000,
      "inbase": "В наличии",
      "cat": "Гематологические"
    },
    {
      "id": "512354626416234323frd427",
      "img": "../img/image 31 (3).png",
      "type": "Автоматические анализаторые",
      "header": "Автоматический гематологический анализатор DF50 Vet",
      "price": 690000,
      "inbase": "Нет в наличии",
      "cat": "Биохимические"
    },
    {
      "id": "512354626416234323frd428",
      "img": "../img/image 31 (2).png",
      "type": "Автоматические анализаторые",
      "header": "Автоматический гематологический анализатор DF50 Vet 1",
      "price": 690000,
      "inbase": "В наличии",
      "cat": "Электрокардиографы"
    },
    {
      "id": "512354626416234323frd429",
      "img": "../img/image 31.png",
      "type": "Автоматические анализаторые",
      "header": "Автоматический гематологический анализатор DF50 Vet",
      "price": 690000,
      "inbase": "Нет в наличии",
      "cat": "Иммуно"
    }
  ],
  "novosti": [
    {
      "id": "1",
      "img": "../img/9e21e6f787e60d58c9dfb6d658401ea1.png",
      "title": "Выставка ЗООИНДУСТРИЯ 2021",
      "paragraph": "Первое ОФЛАЙН бизнес-мероприятие отрасли в 2021 году — выставка товаров и услуг для домашних животных «ЗООИНДУСТРИЯ» — позволит Вам решить ряд стратегически значимых задач"
    },
    {
      "id": "2",
      "img": "../img/9381bedb8f859be8ed44a7f05a306739.png",
      "title": "XXIX Московский Международный Ветеринарный Конгресс",
      "paragraph": "XXIX Московский Международный Ветеринарный Конгресс Уважаемые партнеры, друзья! Наконец-то мы снова переходим в offline–формат нашего общения!  "
    },
    {
      "id": "3",
      "img": "../img/e89291311efbcc0f0c1a3407ee365cad.png",
      "title": "Прайс-листы на 1 квартал 2021 года",
      "paragraph": "Прайс-листы на 1 квартал 2021 года Уважаемые руководители и сотрудники ветеринарных клиники иных ветеринарных организаций! "
    },
    {
      "id": "4",
      "img": "../img/8086165706220db8499b837e8476a5c2.png",
      "title": "Новая версия ПО для Skyla VB1 AS37",
      "paragraph": "Вышла новая версия AS37 программного обеспечения для Skyla VB1 Уважаемые Партнеры, хочу сообщить вам о выходе очередного релиза программного обеспечения для ветеринарного биохимического анализатора Skyla VB1"
    },
    {
      "id": "5",
      "img": "../img/9e21e6f787e60d58c9dfb6d658401ea1.png",
      "title": "Выставка ЗООИНДУСТРИЯ 2021",
      "paragraph": "Первое ОФЛАЙН бизнес-мероприятие отрасли в 2021 году — выставка товаров и услуг для домашних животных «ЗООИНДУСТРИЯ» — позволит Вам решить ряд стратегически значимых задач"
    },
    {
      "id": "6",
      "img": "../img/9381bedb8f859be8ed44a7f05a306739.png",
      "title": "XXIX Московский Международный Ветеринарный Конгресс",
      "paragraph": "XXIX Московский Международный Ветеринарный Конгресс Уважаемые партнеры, друзья! Наконец-то мы снова переходим в offline–формат нашего общения!  "
    },
    {
      "id": "7",
      "img": "../img/e89291311efbcc0f0c1a3407ee365cad.png",
      "title": "Прайс-листы на 1 квартал 2021 года",
      "paragraph": "Прайс-листы на 1 квартал 2021 года Уважаемые руководители и сотрудники ветеринарных клиники иных ветеринарных организаций! "
    },
    {
      "id": "8",
      "img": "../img/8086165706220db8499b837e8476a5c2.png",
      "title": "Новая версия ПО для Skyla VB1 AS37",
      "paragraph": "Вышла новая версия AS37 программного обеспечения для Skyla VB1 Уважаемые Партнеры, хочу сообщить вам о выходе очередного релиза программного обеспечения для ветеринарного биохимического анализатора Skyla VB1"
    },
    {
      "id": "9",
      "img": "../img/9e21e6f787e60d58c9dfb6d658401ea1.png",
      "title": "Выставка ЗООИНДУСТРИЯ 2021",
      "paragraph": "Первое ОФЛАЙН бизнес-мероприятие отрасли в 2021 году — выставка товаров и услуг для домашних животных «ЗООИНДУСТРИЯ» — позволит Вам решить ряд стратегически значимых задач"
    },
    {
      "id": "10",
      "img": "../img/9381bedb8f859be8ed44a7f05a306739.png",
      "title": "XXIX Московский Международный Ветеринарный Конгресс",
      "paragraph": "XXIX Московский Международный Ветеринарный Конгресс Уважаемые партнеры, друзья! Наконец-то мы снова переходим в offline–формат нашего общения!  "
    },
    {
      "id": "11",
      "img": "../img/e89291311efbcc0f0c1a3407ee365cad.png",
      "title": "Прайс-листы на 1 квартал 2021 года",
      "paragraph": "Прайс-листы на 1 квартал 2021 года Уважаемые руководители и сотрудники ветеринарных клиники иных ветеринарных организаций! "
    },
    {
      "id": "12",
      "img": "../img/8086165706220db8499b837e8476a5c2.png",
      "title": "Новая версия ПО для Skyla VB1 AS37",
      "paragraph": "Вышла новая версия AS37 программного обеспечения для Skyla VB1 Уважаемые Партнеры, хочу сообщить вам о выходе очередного релиза программного обеспечения для ветеринарного биохимического анализатора Skyla VB1"
    },
    {
      "id": "13",
      "img": "../img/9e21e6f787e60d58c9dfb6d658401ea1.png",
      "title": "Выставка ЗООИНДУСТРИЯ 2021",
      "paragraph": "Первое ОФЛАЙН бизнес-мероприятие отрасли в 2021 году — выставка товаров и услуг для домашних животных «ЗООИНДУСТРИЯ» — позволит Вам решить ряд стратегически значимых задач"
    },
    {
      "id": "14",
      "img": "../img/9381bedb8f859be8ed44a7f05a306739.png",
      "title": "XXIX Московский Международный Ветеринарный Конгресс",
      "paragraph": "XXIX Московский Международный Ветеринарный Конгресс Уважаемые партнеры, друзья! Наконец-то мы снова переходим в offline–формат нашего общения!  "
    },
    {
      "id": "15",
      "img": "../img/e89291311efbcc0f0c1a3407ee365cad.png",
      "title": "Прайс-листы на 1 квартал 2021 года",
      "paragraph": "Прайс-листы на 1 квартал 2021 года Уважаемые руководители и сотрудники ветеринарных клиники иных ветеринарных организаций! "
    },
    {
      "id": "16",
      "img": "../img/8086165706220db8499b837e8476a5c2.png",
      "title": "Новая версия ПО для Skyla VB1 AS37",
      "paragraph": "Вышла новая версия AS37 программного обеспечения для Skyla VB1 Уважаемые Партнеры, хочу сообщить вам о выходе очередного релиза программного обеспечения для ветеринарного биохимического анализатора Skyla VB1"
    },
    {
      "id": "17",
      "img": "../img/9e21e6f787e60d58c9dfb6d658401ea1.png",
      "title": "Выставка ЗООИНДУСТРИЯ 2021",
      "paragraph": "Первое ОФЛАЙН бизнес-мероприятие отрасли в 2021 году — выставка товаров и услуг для домашних животных «ЗООИНДУСТРИЯ» — позволит Вам решить ряд стратегически значимых задач"
    },
    {
      "id": "18",
      "img": "../img/9381bedb8f859be8ed44a7f05a306739.png",
      "title": "XXIX Московский Международный Ветеринарный Конгресс",
      "paragraph": "XXIX Московский Международный Ветеринарный Конгресс Уважаемые партнеры, друзья! Наконец-то мы снова переходим в offline–формат нашего общения!  "
    },
    {
      "id": "19",
      "img": "../img/e89291311efbcc0f0c1a3407ee365cad.png",
      "title": "Прайс-листы на 1 квартал 2021 года",
      "paragraph": "Прайс-листы на 1 квартал 2021 года Уважаемые руководители и сотрудники ветеринарных клиники иных ветеринарных организаций! "
    },
    {
      "id": "20",
      "img": "../img/8086165706220db8499b837e8476a5c2.png",
      "title": "Новая версия ПО для Skyla VB1 AS37",
      "paragraph": "Вышла новая версия AS37 программного обеспечения для Skyla VB1 Уважаемые Партнеры, хочу сообщить вам о выходе очередного релиза программного обеспечения для ветеринарного биохимического анализатора Skyla VB1"
    },
    {
      "id": "21",
      "img": "../img/9e21e6f787e60d58c9dfb6d658401ea1.png",
      "title": "Выставка ЗООИНДУСТРИЯ 2021",
      "paragraph": "Первое ОФЛАЙН бизнес-мероприятие отрасли в 2021 году — выставка товаров и услуг для домашних животных «ЗООИНДУСТРИЯ» — позволит Вам решить ряд стратегически значимых задач"
    },
    {
      "id": "22",
      "img": "../img/9381bedb8f859be8ed44a7f05a306739.png",
      "title": "XXIX Московский Международный Ветеринарный Конгресс",
      "paragraph": "XXIX Московский Международный Ветеринарный Конгресс Уважаемые партнеры, друзья! Наконец-то мы снова переходим в offline–формат нашего общения!  "
    },
    {
      "id": "23",
      "img": "../img/e89291311efbcc0f0c1a3407ee365cad.png",
      "title": "Прайс-листы на 1 квартал 2021 года",
      "paragraph": "Прайс-листы на 1 квартал 2021 года Уважаемые руководители и сотрудники ветеринарных клиники иных ветеринарных организаций! "
    },
    {
      "id": "24",
      "img": "../img/8086165706220db8499b837e8476a5c2.png",
      "title": "Новая версия ПО для Skyla VB1 AS37",
      "paragraph": "Вышла новая версия AS37 программного обеспечения для Skyla VB1 Уважаемые Партнеры, хочу сообщить вам о выходе очередного релиза программного обеспечения для ветеринарного биохимического анализатора Skyla VB1"
    },
    {
      "id": "25",
      "img": "../img/9e21e6f787e60d58c9dfb6d658401ea1.png",
      "title": "Выставка ЗООИНДУСТРИЯ 2021",
      "paragraph": "Первое ОФЛАЙН бизнес-мероприятие отрасли в 2021 году — выставка товаров и услуг для домашних животных «ЗООИНДУСТРИЯ» — позволит Вам решить ряд стратегически значимых задач"
    },
    {
      "id": "26",
      "img": "../img/9381bedb8f859be8ed44a7f05a306739.png",
      "title": "XXIX Московский Международный Ветеринарный Конгресс",
      "paragraph": "XXIX Московский Международный Ветеринарный Конгресс Уважаемые партнеры, друзья! Наконец-то мы снова переходим в offline–формат нашего общения!  "
    },
    {
      "id": "27",
      "img": "../img/e89291311efbcc0f0c1a3407ee365cad.png",
      "title": "Прайс-листы на 1 квартал 2021 года",
      "paragraph": "Прайс-листы на 1 квартал 2021 года Уважаемые руководители и сотрудники ветеринарных клиники иных ветеринарных организаций! "
    },
    {
      "id": "28",
      "img": "../img/8086165706220db8499b837e8476a5c2.png",
      "title": "Новая версия ПО для Skyla VB1 AS37",
      "paragraph": "Вышла новая версия AS37 программного обеспечения для Skyla VB1 Уважаемые Партнеры, хочу сообщить вам о выходе очередного релиза программного обеспечения для ветеринарного биохимического анализатора Skyla VB1"
    },
    {
      "id": "29",
      "img": "../img/9e21e6f787e60d58c9dfb6d658401ea1.png",
      "title": "Выставка ЗООИНДУСТРИЯ 2021",
      "paragraph": "Первое ОФЛАЙН бизнес-мероприятие отрасли в 2021 году — выставка товаров и услуг для домашних животных «ЗООИНДУСТРИЯ» — позволит Вам решить ряд стратегически значимых задач"
    },
    {
      "id": "30",
      "img": "../img/9381bedb8f859be8ed44a7f05a306739.png",
      "title": "XXIX Московский Международный Ветеринарный Конгресс",
      "paragraph": "XXIX Московский Международный Ветеринарный Конгресс Уважаемые партнеры, друзья! Наконец-то мы снова переходим в offline–формат нашего общения!  "
    },
    {
      "id": "31",
      "img": "../img/e89291311efbcc0f0c1a3407ee365cad.png",
      "title": "Прайс-листы на 1 квартал 2021 года",
      "paragraph": "Прайс-листы на 1 квартал 2021 года Уважаемые руководители и сотрудники ветеринарных клиники иных ветеринарных организаций! "
    },
    {
      "id": "32",
      "img": "../img/8086165706220db8499b837e8476a5c2.png",
      "title": "Новая версия ПО для Skyla VB1 AS37",
      "paragraph": "Вышла новая версия AS37 программного обеспечения для Skyla VB1 Уважаемые Партнеры, хочу сообщить вам о выходе очередного релиза программного обеспечения для ветеринарного биохимического анализатора Skyla VB1"
    },
    {
      "id": "33",
      "img": "../img/9e21e6f787e60d58c9dfb6d658401ea1.png",
      "title": "Выставка ЗООИНДУСТРИЯ 2021",
      "paragraph": "Первое ОФЛАЙН бизнес-мероприятие отрасли в 2021 году — выставка товаров и услуг для домашних животных «ЗООИНДУСТРИЯ» — позволит Вам решить ряд стратегически значимых задач"
    },
    {
      "id": "34",
      "img": "../img/9381bedb8f859be8ed44a7f05a306739.png",
      "title": "XXIX Московский Международный Ветеринарный Конгресс",
      "paragraph": "XXIX Московский Международный Ветеринарный Конгресс Уважаемые партнеры, друзья! Наконец-то мы снова переходим в offline–формат нашего общения!  "
    },
    {
      "id": "35",
      "img": "../img/e89291311efbcc0f0c1a3407ee365cad.png",
      "title": "Прайс-листы на 1 квартал 2021 года",
      "paragraph": "Прайс-листы на 1 квартал 2021 года Уважаемые руководители и сотрудники ветеринарных клиники иных ветеринарных организаций! "
    },
    {
      "id": "36",
      "img": "../img/8086165706220db8499b837e8476a5c2.png",
      "title": "Новая версия ПО для Skyla VB1 AS37",
      "paragraph": "Вышла новая версия AS37 программного обеспечения для Skyla VB1 Уважаемые Партнеры, хочу сообщить вам о выходе очередного релиза программного обеспечения для ветеринарного биохимического анализатора Skyla VB1"
    },
    {
      "id": "37",
      "img": "../img/9e21e6f787e60d58c9dfb6d658401ea1.png",
      "title": "Выставка ЗООИНДУСТРИЯ 2021",
      "paragraph": "Первое ОФЛАЙН бизнес-мероприятие отрасли в 2021 году — выставка товаров и услуг для домашних животных «ЗООИНДУСТРИЯ» — позволит Вам решить ряд стратегически значимых задач"
    },
    {
      "id": "38",
      "img": "../img/9381bedb8f859be8ed44a7f05a306739.png",
      "title": "XXIX Московский Международный Ветеринарный Конгресс",
      "paragraph": "XXIX Московский Международный Ветеринарный Конгресс Уважаемые партнеры, друзья! Наконец-то мы снова переходим в offline–формат нашего общения!  "
    },
    {
      "id": "39",
      "img": "../img/e89291311efbcc0f0c1a3407ee365cad.png",
      "title": "Прайс-листы на 1 квартал 2021 года",
      "paragraph": "Прайс-листы на 1 квартал 2021 года Уважаемые руководители и сотрудники ветеринарных клиники иных ветеринарных организаций! "
    },
    {
      "id": "40",
      "img": "../img/8086165706220db8499b837e8476a5c2.png",
      "title": "Новая версия ПО для Skyla VB1 AS37",
      "paragraph": "Вышла новая версия AS37 программного обеспечения для Skyla VB1 Уважаемые Партнеры, хочу сообщить вам о выходе очередного релиза программного обеспечения для ветеринарного биохимического анализатора Skyla VB1"
    },
    {
      "id": "41",
      "img": "../img/9e21e6f787e60d58c9dfb6d658401ea1.png",
      "title": "Выставка ЗООИНДУСТРИЯ 2021",
      "paragraph": "Первое ОФЛАЙН бизнес-мероприятие отрасли в 2021 году — выставка товаров и услуг для домашних животных «ЗООИНДУСТРИЯ» — позволит Вам решить ряд стратегически значимых задач"
    },
    {
      "id": "42",
      "img": "../img/9381bedb8f859be8ed44a7f05a306739.png",
      "title": "XXIX Московский Международный Ветеринарный Конгресс",
      "paragraph": "XXIX Московский Международный Ветеринарный Конгресс Уважаемые партнеры, друзья! Наконец-то мы снова переходим в offline–формат нашего общения!  "
    },
    {
      "id": "43",
      "img": "../img/e89291311efbcc0f0c1a3407ee365cad.png",
      "title": "Прайс-листы на 1 квартал 2021 года",
      "paragraph": "Прайс-листы на 1 квартал 2021 года Уважаемые руководители и сотрудники ветеринарных клиники иных ветеринарных организаций! "
    },
    {
      "id": "44",
      "img": "../img/8086165706220db8499b837e8476a5c2.png",
      "title": "Новая версия ПО для Skyla VB1 AS37",
      "paragraph": "Вышла новая версия AS37 программного обеспечения для Skyla VB1 Уважаемые Партнеры, хочу сообщить вам о выходе очередного релиза программного обеспечения для ветеринарного биохимического анализатора Skyla VB1"
    },
    {
      "id": "45",
      "img": "../img/9381bedb8f859be8ed44a7f05a306739.png",
      "title": "Выставка ЗООИНДУСТРИЯ 2021",
      "paragraph": "Первое ОФЛАЙН бизнес-мероприятие отрасли в 2021 году — выставка товаров и услуг для домашних животных «ЗООИНДУСТРИЯ» — позволит Вам решить ряд стратегически значимых задач"
    },
    {
      "id": "46",
      "img": "../img/8086165706220db8499b837e8476a5c2.png",
      "title": "XXIX Московский Международный Ветеринарный Конгресс",
      "paragraph": "XXIX Московский Международный Ветеринарный Конгресс Уважаемые партнеры, друзья! Наконец-то мы снова переходим в offline–формат нашего общения!  "
    },
    {
      "id": "47",
      "img": "../img/9381bedb8f859be8ed44a7f05a306739.png",
      "title": "Прайс-листы на 1 квартал 2021 года",
      "paragraph": "Прайс-листы на 1 квартал 2021 года Уважаемые руководители и сотрудники ветеринарных клиники иных ветеринарных организаций! "
    },
    {
      "id": "48",
      "img": "../img/e89291311efbcc0f0c1a3407ee365cad.png",
      "title": "Новая версия ПО для Skyla VB1 AS37",
      "paragraph": "Вышла новая версия AS37 программного обеспечения для Skyla VB1 Уважаемые Партнеры, хочу сообщить вам о выходе очередного релиза программного обеспечения для ветеринарного биохимического анализатора Skyla VB1"
    }
  ],
  "stati": [
    {
      "id": "1",
      "img": "../img/Rectangle 33 (14).png",
      "title": "Рекомендации по техническому обслуживанию лабораторного оборудования",
      "paragraph": "После пусконаладки и ввода в эксплуатацию лабораторное оборудование необходимо периодически проверять и обслуживать."
    },
    {
      "id": "2",
      "img": "../img/Rectangle 33 (15).png",
      "title": "Миниатюризация как тенденция в ветеринарной функциональной диагностике",
      "paragraph": "До появления инструментов функциональной диагностики проверить состояние того или иного органа не всегда было возможно без хирургического вмешательства."
    },
    {
      "id": "3",
      "img": "../img/Rectangle 33 (16).png",
      "title": "Преимущества газового наркоза перед инъекционным",
      "paragraph": "В ветеринарии используется два основных вида наркоза: инъекционный и газовый."
    },
    {
      "id": "4",
      "img": "../img/Rectangle 33 (17).png",
      "title": "Современные DR-панели в ветеринарной практике",
      "paragraph": "DR-панель – это плоскопанельный детектор для рентгенографии."
    },
    {
      "id": "5",
      "img": "../img/Rectangle 33 (14).png",
      "title": "Рекомендации по техническому обслуживанию лабораторного оборудования",
      "paragraph": "После пусконаладки и ввода в эксплуатацию лабораторное оборудование необходимо периодически проверять и обслуживать."
    },
    {
      "id": "6",
      "img": "../img/Rectangle 33 (15).png",
      "title": "Миниатюризация как тенденция в ветеринарной функциональной диагностике",
      "paragraph": "До появления инструментов функциональной диагностики проверить состояние того или иного органа не всегда было возможно без хирургического вмешательства."
    },
    {
      "id": "7",
      "img": "../img/Rectangle 33 (16).png",
      "title": "Преимущества газового наркоза перед инъекционным",
      "paragraph": "В ветеринарии используется два основных вида наркоза: инъекционный и газовый."
    },
    {
      "id": "8",
      "img": "../img/Rectangle 33 (17).png",
      "title": "Современные DR-панели в ветеринарной практике",
      "paragraph": "DR-панель – это плоскопанельный детектор для рентгенографии."
    },
    {
      "id": "9",
      "img": "../img/Rectangle 33 (14).png",
      "title": "Рекомендации по техническому обслуживанию лабораторного оборудования",
      "paragraph": "После пусконаладки и ввода в эксплуатацию лабораторное оборудование необходимо периодически проверять и обслуживать."
    },
    {
      "id": "10",
      "img": "../img/Rectangle 33 (15).png",
      "title": "Миниатюризация как тенденция в ветеринарной функциональной диагностике",
      "paragraph": "До появления инструментов функциональной диагностики проверить состояние того или иного органа не всегда было возможно без хирургического вмешательства."
    },
    {
      "id": "11",
      "img": "../img/Rectangle 33 (16).png",
      "title": "Преимущества газового наркоза перед инъекционным",
      "paragraph": "В ветеринарии используется два основных вида наркоза: инъекционный и газовый."
    },
    {
      "id": "12",
      "img": "../img/Rectangle 33 (17).png",
      "title": "Современные DR-панели в ветеринарной практике",
      "paragraph": "DR-панель – это плоскопанельный детектор для рентгенографии."
    },
    {
      "id": "13",
      "img": "../img/Rectangle 33 (14).png",
      "title": "Рекомендации по техническому обслуживанию лабораторного оборудования",
      "paragraph": "После пусконаладки и ввода в эксплуатацию лабораторное оборудование необходимо периодически проверять и обслуживать."
    },
    {
      "id": "14",
      "img": "../img/Rectangle 33 (15).png",
      "title": "Миниатюризация как тенденция в ветеринарной функциональной диагностике",
      "paragraph": "До появления инструментов функциональной диагностики проверить состояние того или иного органа не всегда было возможно без хирургического вмешательства."
    },
    {
      "id": "15",
      "img": "../img/Rectangle 33 (16).png",
      "title": "Преимущества газового наркоза перед инъекционным",
      "paragraph": "В ветеринарии используется два основных вида наркоза: инъекционный и газовый."
    },
    {
      "id": "16",
      "img": "../img/Rectangle 33 (17).png",
      "title": "Современные DR-панели в ветеринарной практике",
      "paragraph": "DR-панель – это плоскопанельный детектор для рентгенографии."
    },
    {
      "id": "17",
      "img": "../img/Rectangle 33 (14).png",
      "title": "Рекомендации по техническому обслуживанию лабораторного оборудования",
      "paragraph": "После пусконаладки и ввода в эксплуатацию лабораторное оборудование необходимо периодически проверять и обслуживать."
    },
    {
      "id": "18",
      "img": "../img/Rectangle 33 (15).png",
      "title": "Миниатюризация как тенденция в ветеринарной функциональной диагностике",
      "paragraph": "До появления инструментов функциональной диагностики проверить состояние того или иного органа не всегда было возможно без хирургического вмешательства."
    },
    {
      "id": "19",
      "img": "../img/Rectangle 33 (17).png",
      "title": "Преимущества газового наркоза перед инъекционным",
      "paragraph": "В ветеринарии используется два основных вида наркоза: инъекционный и газовый."
    },
    {
      "id": "20",
      "img": "../img/Rectangle 33 (16).png",
      "title": "Современные DR-панели в ветеринарной практике",
      "paragraph": "DR-панель – это плоскопанельный детектор для рентгенографии."
    },
    {
      "id": "21",
      "img": "../img/Rectangle 33 (15).png",
      "title": "Рекомендации по техническому обслуживанию лабораторного оборудования",
      "paragraph": "После пусконаладки и ввода в эксплуатацию лабораторное оборудование необходимо периодически проверять и обслуживать."
    },
    {
      "id": "22",
      "img": "../img/Rectangle 33 (14).png",
      "title": "Миниатюризация как тенденция в ветеринарной функциональной диагностике",
      "paragraph": "До появления инструментов функциональной диагностики проверить состояние того или иного органа не всегда было возможно без хирургического вмешательства."
    },
    {
      "id": "23",
      "img": "../img/Rectangle 33 (17).png",
      "title": "Преимущества газового наркоза перед инъекционным",
      "paragraph": "В ветеринарии используется два основных вида наркоза: инъекционный и газовый."
    },
    {
      "id": "24",
      "img": "../img/Rectangle 33 (16).png",
      "title": "Современные DR-панели в ветеринарной практике",
      "paragraph": "DR-панель – это плоскопанельный детектор для рентгенографии."
    },
    {
      "id": "25",
      "img": "../img/Rectangle 33 (15).png",
      "title": "Рекомендации по техническому обслуживанию лабораторного оборудования",
      "paragraph": "После пусконаладки и ввода в эксплуатацию лабораторное оборудование необходимо периодически проверять и обслуживать."
    },
    {
      "id": "26",
      "img": "../img/Rectangle 33 (14).png",
      "title": "Миниатюризация как тенденция в ветеринарной функциональной диагностике",
      "paragraph": "До появления инструментов функциональной диагностики проверить состояние того или иного органа не всегда было возможно без хирургического вмешательства."
    },
    {
      "id": "27",
      "img": "../img/Rectangle 33 (17).png",
      "title": "Преимущества газового наркоза перед инъекционным",
      "paragraph": "В ветеринарии используется два основных вида наркоза: инъекционный и газовый."
    },
    {
      "id": "28",
      "img": "../img/Rectangle 33 (16).png",
      "title": "Современные DR-панели в ветеринарной практике",
      "paragraph": "DR-панель – это плоскопанельный детектор для рентгенографии."
    },
    {
      "id": "29",
      "img": "../img/Rectangle 33 (15).png",
      "title": "Рекомендации по техническому обслуживанию лабораторного оборудования",
      "paragraph": "После пусконаладки и ввода в эксплуатацию лабораторное оборудование необходимо периодически проверять и обслуживать."
    },
    {
      "id": "30",
      "img": "../img/Rectangle 33 (14).png",
      "title": "Миниатюризация как тенденция в ветеринарной функциональной диагностике",
      "paragraph": "До появления инструментов функциональной диагностики проверить состояние того или иного органа не всегда было возможно без хирургического вмешательства."
    },
    {
      "id": "31",
      "img": "../img/Rectangle 33 (16).png",
      "title": "Преимущества газового наркоза перед инъекционным",
      "paragraph": "В ветеринарии используется два основных вида наркоза: инъекционный и газовый."
    },
    {
      "id": "32",
      "img": "../img/Rectangle 33 (15).png",
      "title": "Современные DR-панели в ветеринарной практике",
      "paragraph": "DR-панель – это плоскопанельный детектор для рентгенографии."
    },
    {
      "id": "33",
      "img": "../img/Rectangle 33 (17).png",
      "title": "Рекомендации по техническому обслуживанию лабораторного оборудования",
      "paragraph": "После пусконаладки и ввода в эксплуатацию лабораторное оборудование необходимо периодически проверять и обслуживать."
    },
    {
      "id": "34",
      "img": "../img/Rectangle 33 (16).png",
      "title": "Миниатюризация как тенденция в ветеринарной функциональной диагностике",
      "paragraph": "До появления инструментов функциональной диагностики проверить состояние того или иного органа не всегда было возможно без хирургического вмешательства."
    },
    {
      "id": "35",
      "img": "../img/Rectangle 33 (15).png",
      "title": "Преимущества газового наркоза перед инъекционным",
      "paragraph": "В ветеринарии используется два основных вида наркоза: инъекционный и газовый."
    },
    {
      "id": "36",
      "img": "../img/Rectangle 33 (14).png",
      "title": "Современные DR-панели в ветеринарной практике",
      "paragraph": "DR-панель – это плоскопанельный детектор для рентгенографии."
    },
    {
      "id": "37",
      "img": "../img/Rectangle 33 (16).png",
      "title": "Рекомендации по техническому обслуживанию лабораторного оборудования",
      "paragraph": "После пусконаладки и ввода в эксплуатацию лабораторное оборудование необходимо периодически проверять и обслуживать."
    },
    {
      "id": "38",
      "img": "../img/Rectangle 33 (17).png",
      "title": "Миниатюризация как тенденция в ветеринарной функциональной диагностике",
      "paragraph": "До появления инструментов функциональной диагностики проверить состояние того или иного органа не всегда было возможно без хирургического вмешательства."
    },
    {
      "id": "39",
      "img": "../img/Rectangle 33 (15).png",
      "title": "Преимущества газового наркоза перед инъекционным",
      "paragraph": "В ветеринарии используется два основных вида наркоза: инъекционный и газовый."
    },
    {
      "id": "40",
      "img": "../img/Rectangle 33 (16).png",
      "title": "Современные DR-панели в ветеринарной практике",
      "paragraph": "DR-панель – это плоскопанельный детектор для рентгенографии."
    }
  ]
}